py_rl_toolkit-0.1.0.dist-info/licenses/LICENSE
rltoolkit/__init__.py
rltoolkit/algorithms.py
rltoolkit/environments.py
rltoolkit/policies.py
rltoolkit/utils.py
py_rl_toolkit-0.1.0.dist-info/METADATA
py_rl_toolkit-0.1.0.dist-info/WHEEL
py_rl_toolkit-0.1.0.dist-info/top_level.txt
py_rl_toolkit-0.1.0.dist-info/RECORD
