Metadata-Version: 2.4
Name: py-rl-toolkit
Version: 0.1.0
Summary: A comprehensive, easy-to-use Python toolkit for reinforcement learning research and education
Author-email: RL Toolkit Team <rltoolkit@example.com>
Maintainer-email: RL Toolkit Team <rltoolkit@example.com>
License: MIT License
Project-URL: Homepage, https://github.com/Nits1627/PyPiRL
Project-URL: Documentation, https://github.com/Nits1627/PyPiRL/blob/main/docs.md
Project-URL: Repository, https://github.com/Nits1627/PyPiRL.git
Project-URL: Bug Tracker, https://github.com/Nits1627/PyPiRL/issues
Keywords: reinforcement learning,machine learning,AI,Q-learning,DQN,SARSA
Classifier: Development Status :: 4 - Beta
Classifier: Intended Audience :: Developers
Classifier: Intended Audience :: Education
Classifier: Intended Audience :: Science/Research
Classifier: License :: OSI Approved :: MIT License
Classifier: Programming Language :: Python :: 3
Classifier: Programming Language :: Python :: 3.7
Classifier: Programming Language :: Python :: 3.8
Classifier: Programming Language :: Python :: 3.9
Classifier: Programming Language :: Python :: 3.10
Classifier: Programming Language :: Python :: 3.11
Classifier: Topic :: Scientific/Engineering :: Artificial Intelligence
Classifier: Topic :: Software Development :: Libraries :: Python Modules
Classifier: Operating System :: OS Independent
Requires-Python: >=3.7
License-File: LICENSE
Requires-Dist: numpy>=1.19.0
Requires-Dist: matplotlib>=3.3.0
Requires-Dist: tqdm>=4.60.0
Provides-Extra: torch
Requires-Dist: torch>=1.9.0; extra == "torch"
Provides-Extra: dev
Requires-Dist: pytest>=6.0; extra == "dev"
Requires-Dist: pytest-cov>=2.0; extra == "dev"
Requires-Dist: black>=21.0; extra == "dev"
Requires-Dist: flake8>=3.8; extra == "dev"
Requires-Dist: twine>=3.0; extra == "dev"
Dynamic: license-file
